[
  {
    "id": "fantasy_king",
    "world": "fantasy",
    "name": "الملك التائه",
    "title": "حارس العرش المكسور",
    "image_url": "",
    "personality": "حكيم، متعب، يحمل أسرار مملكته",
    "topics": [
      {
        "id": "ask_world",
        "label": "اسأله عن العالم",
        "emoji": "🌍",
        "response": "كان هذا العالم جميلاً قبل أن تبدأ الحروب... لكل مملكة ثمن تدفعه للبقاء."
      },
      {
        "id": "ask_advice",
        "label": "اطلب نصيحة",
        "emoji": "📜",
        "response": "القوة وحدها لا تبني مملكة. الحكمة هي ما يبقيها."
      },
      {
        "id": "challenge",
        "label": "تحدّه",
        "emoji": "⚔️",
        "response": "أنت شجاع... أو متهور. في هذا العالم، الفرق بينهما رفيع جداً."
      }
    ],
    "archetype_responses": {
      "warrior":    "أرى في عينيك نار المحارب. وجّهها بحكمة وستغزو العالم.",
      "strategist": "عقلك يعمل باستمرار. هذا ما يميز الملوك عن الجنود.",
      "shadow":     "تخفي كثيراً... لكنني أرى ما وراء القناع.",
      "guardian":   "من تحمي؟ كل حارس يحتاج إلى شيء يستحق الحماية."
    }
  },
  {
    "id": "fantasy_witch",
    "world": "fantasy",
    "name": "الساحرة المنسية",
    "title": "عرافة الغابة",
    "image_url": "",
    "personality": "غامضة، هادئة، تتحدث بالألغاز",
    "topics": [
      {
        "id": "ask_magic",
        "label": "اسألها عن السحر",
        "emoji": "✨",
        "response": "السحر ليس قوة تُمتلك، بل هو استعارة لطاقة الروح."
      },
      {
        "id": "ask_advice",
        "label": "اطلب نصيحة",
        "emoji": "📜",
        "response": "لا تبحث عن الإجابات في النور وحدك، فالظلام يحمل حقائق مخفية."
      }
    ],
    "archetype_responses": {
      "seeker": "أنت باحث عن المعرفة. لكن احذر، فبعض المعارف قد تستهلكك.",
      "oracle": "نرى نفس الأشياء، لكننا نفسرها بطرق مختلفة.",
      "wanderer": "الطريق الذي تسلكه ليس له نهاية، استمتع بالرحلة."
    }
  }
]