{
  "id": 204,
  "title": "المحطة الأخيرة",
  "theme": "أزمات الفضاء",
  "series": 1,
  "game_mode": "multi",
  "description": "طاقم محطة فضائية معزولة يواجه أزمة تلو الأخرى — كل قرار قد يكون الأخير.",
  "start_scene": "scene_01",
  "image_url": "",
  "scenes": [
    {
      "id": "scene_01",
      "title": "المشهد 1",
      "text": "[PLACEHOLDER]",
      "choices": [
        {
          "text": "[PLACEHOLDER]",
          "next_scene": "scene_02"
        },
        {
          "text": "[PLACEHOLDER]",
          "next_scene": "scene_02"
        }
      ]
    },
    {
      "id": "scene_02",
      "title": "المشهد 2",
      "text": "[PLACEHOLDER]",
      "choices": [
        {
          "text": "[PLACEHOLDER]",
          "next_scene": "scene_03"
        },
        {
          "text": "[PLACEHOLDER]",
          "next_scene": "scene_03"
        }
      ]
    },
    {
      "id": "scene_03",
      "title": "المشهد 3",
      "text": "[PLACEHOLDER]",
      "choices": [
        {
          "text": "[PLACEHOLDER]",
          "next_scene": "scene_04"
        },
        {
          "text": "[PLACEHOLDER]",
          "next_scene": "scene_04"
        }
      ]
    },
    {
      "id": "scene_04",
      "title": "المشهد 4",
      "text": "[PLACEHOLDER]",
      "choices": [
        {
          "text": "[PLACEHOLDER]",
          "next_scene": "scene_05"
        },
        {
          "text": "[PLACEHOLDER]",
          "next_scene": "scene_05"
        }
      ]
    },
    {
      "id": "scene_05",
      "title": "المشهد 5",
      "text": "[PLACEHOLDER]",
      "choices": [
        {
          "text": "[PLACEHOLDER]",
          "next_scene": "scene_06"
        },
        {
          "text": "[PLACEHOLDER]",
          "next_scene": "scene_06"
        }
      ]
    },
    {
      "id": "scene_06",
      "title": "المشهد 6",
      "text": "[PLACEHOLDER]",
      "choices": [
        {
          "text": "[PLACEHOLDER]",
          "next_scene": "scene_07"
        },
        {
          "text": "[PLACEHOLDER]",
          "next_scene": "scene_07"
        }
      ]
    },
    {
      "id": "scene_07",
      "title": "المشهد 7",
      "text": "[PLACEHOLDER]",
      "choices": [
        {
          "text": "[PLACEHOLDER]",
          "next_scene": "scene_08"
        },
        {
          "text": "[PLACEHOLDER]",
          "next_scene": "scene_08"
        }
      ]
    },
    {
      "id": "scene_08",
      "title": "المشهد 8",
      "text": "[PLACEHOLDER]",
      "choices": [
        {
          "text": "[PLACEHOLDER]",
          "next_scene": "scene_09"
        },
        {
          "text": "[PLACEHOLDER]",
          "next_scene": "scene_09"
        }
      ]
    },
    {
      "id": "scene_09",
      "title": "المشهد 9",
      "text": "[PLACEHOLDER]",
      "choices": [
        {
          "text": "[PLACEHOLDER]",
          "next_scene": "scene_10"
        },
        {
          "text": "[PLACEHOLDER]",
          "next_scene": "scene_10"
        }
      ]
    },
    {
      "id": "scene_10",
      "title": "المشهد 10",
      "text": "[PLACEHOLDER]",
      "choices": [
        {
          "text": "[PLACEHOLDER]",
          "next_scene": "scene_11"
        },
        {
          "text": "[PLACEHOLDER]",
          "next_scene": "scene_11"
        }
      ]
    },
    {
      "id": "scene_11",
      "title": "المشهد 11",
      "text": "[PLACEHOLDER]",
      "choices": [
        {
          "text": "[PLACEHOLDER]",
          "next_scene": "scene_12"
        },
        {
          "text": "[PLACEHOLDER]",
          "next_scene": "scene_12"
        }
      ]
    },
    {
      "id": "scene_12",
      "title": "المشهد 12",
      "text": "[PLACEHOLDER]",
      "choices": [
        {
          "text": "[PLACEHOLDER]",
          "next_scene": "scene_13"
        },
        {
          "text": "[PLACEHOLDER]",
          "next_scene": "scene_13"
        }
      ]
    },
    {
      "id": "scene_13",
      "title": "المشهد 13",
      "text": "[PLACEHOLDER]",
      "choices": [
        {
          "text": "[PLACEHOLDER]",
          "next_scene": "scene_14"
        },
        {
          "text": "[PLACEHOLDER]",
          "next_scene": "scene_14"
        }
      ]
    },
    {
      "id": "scene_14",
      "title": "المشهد 14",
      "text": "[PLACEHOLDER]",
      "choices": [
        {
          "text": "[PLACEHOLDER]",
          "next_scene": "scene_15"
        },
        {
          "text": "[PLACEHOLDER]",
          "next_scene": "scene_15"
        }
      ]
    },
    {
      "id": "scene_15",
      "title": "المشهد 15",
      "text": "[PLACEHOLDER]",
      "choices": [
        {
          "text": "[PLACEHOLDER]",
          "next_scene": "scene_16"
        },
        {
          "text": "[PLACEHOLDER]",
          "next_scene": "scene_16"
        }
      ]
    },
    {
      "id": "scene_16",
      "title": "المشهد 16",
      "text": "[PLACEHOLDER]",
      "choices": [
        {
          "text": "[PLACEHOLDER]",
          "next_scene": "scene_17"
        },
        {
          "text": "[PLACEHOLDER]",
          "next_scene": "scene_17"
        }
      ]
    },
    {
      "id": "scene_17",
      "title": "المشهد 17",
      "text": "[PLACEHOLDER]",
      "choices": [
        {
          "text": "[PLACEHOLDER]",
          "next_scene": "scene_18"
        },
        {
          "text": "[PLACEHOLDER]",
          "next_scene": "scene_18"
        }
      ]
    },
    {
      "id": "scene_18",
      "title": "المشهد 18",
      "text": "[PLACEHOLDER]",
      "choices": [
        {
          "text": "[PLACEHOLDER]",
          "next_scene": "scene_19"
        },
        {
          "text": "[PLACEHOLDER]",
          "next_scene": "scene_19"
        }
      ]
    },
    {
      "id": "scene_19",
      "title": "المشهد 19",
      "text": "[PLACEHOLDER]",
      "choices": [
        {
          "text": "[PLACEHOLDER]",
          "next_scene": "scene_20"
        },
        {
          "text": "[PLACEHOLDER]",
          "next_scene": "scene_20"
        }
      ]
    },
    {
      "id": "scene_20",
      "title": "المشهد 20",
      "text": "[PLACEHOLDER]",
      "choices": [
        {
          "text": "[PLACEHOLDER]",
          "next_scene": "scene_21"
        },
        {
          "text": "[PLACEHOLDER]",
          "next_scene": "scene_21"
        }
      ]
    },
    {
      "id": "scene_21",
      "title": "المشهد 21",
      "text": "[PLACEHOLDER]",
      "choices": [
        {
          "text": "[PLACEHOLDER]",
          "next_scene": "scene_22"
        },
        {
          "text": "[PLACEHOLDER]",
          "next_scene": "scene_22"
        }
      ]
    },
    {
      "id": "scene_22",
      "title": "المشهد 22",
      "text": "[PLACEHOLDER]",
      "choices": [
        {
          "text": "[PLACEHOLDER]",
          "next_scene": "scene_23"
        },
        {
          "text": "[PLACEHOLDER]",
          "next_scene": "scene_23"
        }
      ]
    },
    {
      "id": "scene_23",
      "title": "المشهد 23",
      "text": "[PLACEHOLDER]",
      "choices": [
        {
          "text": "[PLACEHOLDER]",
          "next_scene": "scene_24"
        },
        {
          "text": "[PLACEHOLDER]",
          "next_scene": "scene_24"
        }
      ]
    },
    {
      "id": "scene_24",
      "title": "المشهد 24",
      "text": "[PLACEHOLDER]",
      "choices": [
        {
          "text": "[PLACEHOLDER]",
          "next_scene": "scene_25"
        },
        {
          "text": "[PLACEHOLDER]",
          "next_scene": "scene_25"
        }
      ]
    },
    {
      "id": "scene_25",
      "title": "المشهد 25",
      "text": "[PLACEHOLDER]",
      "choices": [
        {
          "text": "[PLACEHOLDER]",
          "next_scene": "scene_26"
        },
        {
          "text": "[PLACEHOLDER]",
          "next_scene": "scene_26"
        }
      ]
    },
    {
      "id": "scene_26",
      "title": "المشهد 26",
      "text": "[PLACEHOLDER]",
      "choices": [
        {
          "text": "[PLACEHOLDER]",
          "next_scene": "scene_27"
        },
        {
          "text": "[PLACEHOLDER]",
          "next_scene": "scene_27"
        }
      ]
    },
    {
      "id": "scene_27",
      "title": "المشهد 27",
      "text": "[PLACEHOLDER]",
      "choices": [
        {
          "text": "[PLACEHOLDER]",
          "next_scene": "scene_28"
        },
        {
          "text": "[PLACEHOLDER]",
          "next_scene": "scene_28"
        }
      ]
    },
    {
      "id": "scene_28",
      "title": "المشهد 28",
      "text": "[PLACEHOLDER]",
      "choices": [
        {
          "text": "[PLACEHOLDER]",
          "next_scene": "scene_29"
        },
        {
          "text": "[PLACEHOLDER]",
          "next_scene": "scene_29"
        }
      ]
    },
    {
      "id": "scene_29",
      "title": "المشهد 29",
      "text": "[PLACEHOLDER]",
      "choices": [
        {
          "text": "[PLACEHOLDER]",
          "next_scene": "scene_30"
        },
        {
          "text": "[PLACEHOLDER]",
          "next_scene": "scene_30"
        }
      ]
    },
    {
      "id": "scene_30",
      "title": "القرار الأخير",
      "text": "[PLACEHOLDER]",
      "choices": [
        {
          "text": "[PLACEHOLDER]",
          "next_scene": "ending_win"
        },
        {
          "text": "[PLACEHOLDER]",
          "next_scene": "ending_fail"
        },
        {
          "text": "[PLACEHOLDER]",
          "next_scene": "ending_betrayal"
        }
      ]
    },
    {
      "id": "ending_win",
      "title": "فوز جماعي",
      "text": "[PLACEHOLDER]",
      "is_ending": true,
      "ending_type": "victory",
      "choices": []
    },
    {
      "id": "ending_fail",
      "title": "فشل جماعي",
      "text": "[PLACEHOLDER]",
      "is_ending": true,
      "ending_type": "defeat",
      "choices": []
    },
    {
      "id": "ending_betrayal",
      "title": "خيانة",
      "text": "[PLACEHOLDER]",
      "is_ending": true,
      "ending_type": "defeat",
      "choices": []
    }
  ]
}